geotran/__init__.py
geotran/raster.py
geotran-0.1.5.dist-info/LICENSE.txt
geotran-0.1.5.dist-info/METADATA
geotran-0.1.5.dist-info/WHEEL
geotran-0.1.5.dist-info/top_level.txt
geotran-0.1.5.dist-info/RECORD
