Metadata-Version: 2.1
Name: geotran
Version: 0.1.5
Summary: Python Geospatial Library
Home-page: https://github.com/tnmthai/geotran
Author: Thai Tran
Author-email: tnmthai@gmail.com
License: MIT
Project-URL: Bug Tracker, https://github.com/tnmthai/geotran/issues
Project-URL: repository, https://github.com/tnmthai/geotran
Classifier: Programming Language :: Python :: 3
Classifier: License :: OSI Approved :: MIT License
Classifier: Operating System :: OS Independent
Requires-Python: >=3.6
License-File: LICENSE.txt
